{
    "title": "Java",
    "website": "https://www.java.com/",
    "links": {
        "facebook": "https://www.facebook.com/ilovejava",
        "twitter": "java",
        "wikipedia": "https://en.wikipedia.org/wiki/Java_(programming_language)"
    },
    "logos": [
        "- java-horizontal.svg"
    ],
    "other": {
        "font": "",
        "name": "Sun Semi Bold",
        "url": "http://www.lucasfonts.com/fonts/sun/sun/styles/",
        "guide": "http://www.oracle.com/us/technologies/java/java-licensing-logo-guidelines-1908204.pdf",
        "logohandle": "java",
        "sort": "java",
        "tags": "",
        "youtube": "https://www.youtube.com/java",
        "https": "//upload.wikimedia.org/wikipedia/de/e/e1/Java-Logo.svg)"
    }
}